azure_telemetry/__init__.py
azure_telemetry/logger.py
azure_telemetry/storage.py
azure_telemetry-0.1.0.dist-info/LICENSE
azure_telemetry-0.1.0.dist-info/METADATA
azure_telemetry-0.1.0.dist-info/WHEEL
azure_telemetry-0.1.0.dist-info/top_level.txt
azure_telemetry-0.1.0.dist-info/RECORD
